<?xml version="1.0" encoding="utf-8" ?>
<dwsync>
<file name="noorder.tpl" server="michigan-acupuncture.com//home/webadmin/michigan-acupuncture.com/html/" local="129394669100000000" remote="129394669100000000" />
<file name="test.tpl" server="michigan-acupuncture.com//home/webadmin/michigan-acupuncture.com/html/" local="129394661590000000" remote="129394661590000000" />
<file name="vieworderprofiledetails.tpl" server="michigan-acupuncture.com//home/webadmin/michigan-acupuncture.com/html/" local="129394669120000000" remote="129394669120000000" />
<file name="guestorders.tpl" server="michigan-acupuncture.com//home/webadmin/michigan-acupuncture.com/html/" local="129394669090000000" remote="129394669090000000" />
<file name="view.tpl" server="michigan-acupuncture.com//home/webadmin/michigan-acupuncture.com/html/" local="129394669120000000" remote="129394669120000000" />
<file name="addtrackingtoproduct.tpl" server="michigan-acupuncture.com//home/webadmin/michigan-acupuncture.com/html/" local="129394661560000000" remote="129394661560000000" />
<file name="index.tpl" server="michigan-acupuncture.com//home/webadmin/michigan-acupuncture.com/html/" local="129394669090000000" remote="129394669090000000" />
<file name="verification.tpl" server="michigan-acupuncture.com//home/webadmin/michigan-acupuncture.com/html/" local="129394661590000000" remote="129394661590000000" />
<file name="soldorders.tpl" server="michigan-acupuncture.com//home/webadmin/michigan-acupuncture.com/html/" local="129394669110000000" remote="129394669110000000" />
<file name="_message.tpl" server="michigan-acupuncture.com//home/webadmin/michigan-acupuncture.com/html/" local="129394669120000000" remote="129394669120000000" />
<file name="productstat.tpl" server="michigan-acupuncture.com//home/webadmin/michigan-acupuncture.com/html/" local="129394669100000000" remote="129394669100000000" />
<file name="orders.tpl" server="michigan-acupuncture.com//home/webadmin/michigan-acupuncture.com/html/" local="129394669100000000" remote="129394669100000000" />
</dwsync>